{
  "extensionName": {
    "message": "Mozilla VPN 擴充套件",
    "description": "Name of the extension."
  },
  "extensionDescription": {
    "message": "將 VPN 功能直接整合進 Firefox：可排除特定分頁、設定網站位置，還有更多功能！",
    "description": "Description of the extension."
  },
  "back": {
    "message": "上一頁",
    "description": "Alternative text attribute for back button."
  },
  "productName": {
    "message": "Mozilla VPN",
    "description": "Name of the product."
  },
  "titleServerList": {
    "message": "網站位置",
    "description": "Title for a dialog where users can set the location for a website."
  },
  "selectWebsiteLocation": {
    "message": "請選擇網站位置",
    "description": "Button label."
  },
  "titlePageSettings": {
    "message": "對此網站的偏好設定",
    "description": "The header for website specific settings, i.e. exclude a page from VPN."
  },
  "excludePageFor": {
    "message": "總是關閉 $ORIGIN$ 的 VPN 保護",
    "description": "Setting to exclude a website from VPN.",
    "placeholders": {
      "origin": {
        "content": "$1",
        "example": "developer.mozilla.org"
      }
    }
  },
  "resetPageSettings": {
    "message": "重設網站偏好設定",
    "description": "Button text to reset all site specific settings."
  },
  "vpnIsOn": {
    "message": "已開啟 Firefox 的 VPN 保護",
    "description": "Header to signal that VPN connection is enabled."
  },
  "vpnIsOff": {
    "message": "已關閉 Firefox 的 VPN 保護",
    "description": "Header to signal that VPN connection is disabled."
  },
  "extensionVpnIsOff": {
    "message": "Mozilla VPN 仍然開啟中，正在保護您電腦上的其他程式連線。",
    "description": "Popup subtitle when the extension VPN is off, but the client VPN is on."
  },
  "vpnOffStatus": {
    "message": "關閉",
    "description": "Label indicating that the VPN is off."
  },
  "vpnOnStatus": {
    "message": "開啟",
    "description": "Label indicating that the VPN is on."
  },
  "placeholderSearchWebsites": {
    "message": "搜尋網站",
    "description": "Placeholder text for the search input field to search websites."
  },
  "tableHeadingWebsite": {
    "message": "網站",
    "description": "Table heading for the column listing websites."
  },
  "tableHeadingVpnStatus": {
    "message": "網站保護",
    "description": "Table heading for the column indicating whether the VPN is on or off for a website."
  },
  "headlineNoWebsitePreferences": {
    "message": "您尚未設定任何網站偏好設定",
    "description": "Headline shown when the user hasn’t set any website preferences."
  },
  "noWebsitePreferencesSubText": {
    "message": "您可以透過 Firefox 的擴充套件針對特定網站關閉 Mozilla VPN 保護，或是使用不同地點來連線。要這樣做，請開啟網站、開啟擴充套件，然後調整網站偏好設定。",
    "description": "Subtext shown when there are no website preferences set by the user."
  },
  "altTextRemoveWebsiteButton": {
    "message": "移除 $ORIGIN$ 的規則",
    "description": "Alternative text for the button that removes a website rule from the list of preferences.",
    "placeholders": {
      "origin": {
        "content": "$1",
        "example": "developer.mozilla.org"
      }
    }
  },
  "altTextOpenSettingsPage": {
    "message": "開啟設定頁面",
    "description": "Alternative text for the button that opens the Extensions Settings page."
  },
  "searchServer": {
    "message": "搜尋位置",
    "description": "Placeholder for the Input field where users can search the list of servers."
  },
  "titleSubscribeNow": {
    "message": "訂閱 Mozilla VPN。"
  },
  "bodySubscribeNow": {
    "message": "看來您還沒有訂閱 Mozilla VPN。若要使用此擴充套件，請先訂閱。",
    "description": "Body of an error message, shown if the user is trying to use the extension without a subscription."
  },
  "btnSubscribeNow": {
    "message": "立即訂閱",
    "description": "Call to action button for users to subscribe to Mozilla VPN."
  },
  "getHelp": {
    "message": "取得幫助",
    "description": "Text of a link pointing to a relevant help page."
  },
  "headerOpenMozillaVPN": {
    "message": "開啟 Mozilla VPN",
    "description": "Headline."
  },
  "headerSignedOut": {
    "message": "登入 Mozilla VPN 應用程式。"
  },
  "bodySignedOut": {
    "message": "您目前未登入 Mozilla VPN 應用程式。若要使用 Firefox 的 Mozilla VPN 擴充套件，請開啟電腦上的 VPN 程式並登入帳號。"
  },
  "btnOpenVpn": {
    "message": "開啟 Mozilla VPN。"
  },
  "headerNeedsUpdate": {
    "message": "更新 Mozilla VPN",
    "description": "This is the headline of an error panel."
  },
  "bodyNeedsUpdate": {
    "message": "若要使用此擴充套件，必須安裝最新版的 Mozilla VPN 應用程式。",
    "description": "This is the body copy for an error panel."
  },
  "headerInstallMsg": {
    "message": "安裝 Mozilla VPN",
    "description": "Header if a VPN installation was not found."
  },
  "bodyOpenMsg": {
    "message": "若要使用 Firefox 的 Mozilla VPN 擴充套件，請先開啟 Mozilla VPN。",
    "description": "Popup subtitle text."
  },
  "bodyInstallMsg": {
    "message": "若要使用此擴充套件，請先下載安裝 Mozilla VPN 到您的電腦。"
  },
  "bodyInstallMsgFooter": {
    "message": "註：Mozilla VPN 是需付費的訂閱服務。",
    "description": "This is a footnote for “bodyInstallMsg”."
  },
  "btnDownloadNow": {
    "message": "立刻下載",
    "description": "This is a call to action button to download the VPN."
  },
  "defaultLocationHeader": {
    "message": "使用 Mozilla VPN 的位置。"
  },
  "useDefaultLocationExplainer": {
    "message": "使用這台電腦上的 Mozilla VPN 的連線位置。",
    "description": "Explanation of what “Use default Mozilla VPN Location” means."
  },
  "headerUnsupportedOSMessage": {
    "message": "不支援的平台。"
  },
  "bodyUnsupportedOSMessage": {
    "message": "目前 Mozilla VPN 擴充套件僅支援 Windows 裝置。"
  },
  "footnoteUnsupportedOSMessage": {
    "message": "我們正在努力，希望很快就能支援 macOS 與 Linux！"
  },
  "turnOnProtection": {
    "message": "開啟保護",
    "description": "Button label."
  },
  "removeCustomLocation": {
    "message": "移除自訂位置",
    "description": "Button label."
  },
  "websiteProtection": {
    "message": "網站保護",
    "description": "A subtitle that is followed by an off icon and the word 'Off'."
  },
  "giveFeedback": {
    "message": "提供意見回饋",
    "description": "Button label."
  },
  "learnMore": {
    "message": "更多資訊",
    "description": "Label of link that leads to SUMO."
  },
  "onboarding1_title": {
    "message": "對特定網站關閉 VPN",
    "description": "Title in onboarding panel."
  },
  "onboarding2_title": {
    "message": "從不同位置開啟不同網站",
    "description": "Title in onboarding panel."
  },
  "next": {
    "message": "下一步",
    "description": "Label of button to progress to next onboarding panel."
  },
  "skip": {
    "message": "略過",
    "description": "Label of button to skip onboarding."
  },
  "headerReEnableFirefoxProtection": {
    "message": "重新開啟 Firefox 保護",
    "description": "Error panel title for when Firefox is an excluded app."
  },
  "settingsPageTitle": {
    "message": "Mozilla VPN 網站偏好設定",
    "description": "Title for settings page tab."
  },
  "noSignal": {
    "message": "無訊號",
    "description": "Indicator text describing the status of the VPN."
  },
  "unstable": {
    "message": "不穩定",
    "description": "Indicator text describing the status of the VPN."
  },
  "connecting": {
    "message": "連線中…",
    "description": "Indicator text describing the status of the VPN."
  },
  "helpCenter": {
    "message": "說明中心",
    "description": "Link title."
  },
  "websitePreferences": {
    "message": "網站偏好設定",
    "description": "Link title."
  },
  "contactSupport": {
    "message": "聯絡支援團隊",
    "description": "Link title."
  },
  "offForWebsite": {
    "message": "對網站關閉 Mozilla VPN",
    "description": "Aria label."
  },
  "websiteLocationLabel": {
    "message": "$SERVERLOCATION$：Mozilla VPN 網站位置",
    "description": "Aria label for a flag icon representing the location of the VPN server",
    "placeholders": {
      "serverlocation": {
        "content": "$1",
        "example": "Germany"
      }
    }
  }
}
